LICENSE.txt
MANIFEST.in
README.md
setup.py
iceweather/__init__.py
iceweather/stations.py
iceweather/util.py
iceweather/weather.py
iceweather.egg-info/PKG-INFO
iceweather.egg-info/SOURCES.txt
iceweather.egg-info/dependency_links.txt
iceweather.egg-info/requires.txt
iceweather.egg-info/top_level.txt
iceweather.egg-info/zip-safe