Metadata-Version: 2.1
Name: iceweather
Version: 0.2.3
Summary: Look up Icelandic weather information (observations, forecasts, etc.)
Home-page: https://github.com/mideind/iceweather
Author: Miðeind ehf.
Author-email: mideind@mideind.is
License: BSD
Classifier: License :: OSI Approved :: BSD License
Classifier: Operating System :: OS Independent
Classifier: Development Status :: 5 - Production/Stable
Classifier: Intended Audience :: Developers
Classifier: Programming Language :: Python
Classifier: Programming Language :: Python :: 3.7
Classifier: Programming Language :: Python :: 3.8
Classifier: Programming Language :: Python :: 3.9
Classifier: Programming Language :: Python :: 3.10
Classifier: Programming Language :: Python :: 3.11
Classifier: Topic :: Software Development :: Libraries :: Python Modules
Classifier: Topic :: Utilities
License-File: LICENSE.txt
